[
    {
        "0": "December 2018",
        "1": "January 2019",
        "2": "February 2019",
        "3": "March 2019",
        "4": "April 2019",
        "5": "May 2019",
        "6": "June 2019",
        "7": "July 2019",
        "8": "August 2019",
        "9": "September 2019",
        "10": "October 2019",
        "11": "November 2019",
        "12": "December 2019",
        "13": "January 2020",
        "14": "February 2020",
        "15": "March 2020",
        "16": "April 2020",
        "17": "May 2020",
        "18": "June 2020",
        "19": "July 2020",
        "20": "August 2020",
        "21": "September 2020",
        "22": "October 2020",
        "23": "November 2020",
        "24": "December 2020",
        "25": "January 2021",
        "26": "February 2021",
        "27": "March 2021",
        "28": "April 2021",
        "29": "May 2021",
        "30": "June 2021",
        "31": "July 2021",
        "32": "August 2021",
        "33": "September 2021",
        "34": "October 2021",
        "35": "November 2021",
        "36": "December 2021",
        "37": "January 2022",
        "38": "February 2022",
        "39": "March 2022",
        "40": "April 2022",
        "41": "May 2022",
        "42": "June 2022",
        "43": "July 2022",
        "44": "August 2022",
        "45": "September 2022",
        "46": "October 2022",
        "47": "November 2022",
        "48": "December 2022",
        "49": "January 2023",
        "50": "February 2023",
        "51": "March 2023",
        "52": "April 2023",
        "53": "May 2023",
        "54": "June 2023",
        "55": "July 2023",
        "56": "August 2023",
        "57": "September 2023",
        "58": "October 2023",
        "59": "November 2023"
    },
    {
        "0": 33621,
        "1": 54046,
        "2": 52730,
        "3": 64424,
        "4": 52533,
        "5": 51798,
        "6": 52621,
        "7": 44665,
        "8": 54275,
        "9": 47119,
        "10": 50902,
        "11": 50230,
        "12": 40403,
        "13": 58367,
        "14": 72926,
        "15": 53134,
        "16": 71431,
        "17": 82869,
        "18": 75157,
        "19": 63084,
        "20": 71621,
        "21": 58837,
        "22": 58284,
        "23": 57113,
        "24": 56794,
        "25": 66481,
        "26": 61293,
        "27": 70402,
        "28": 69319,
        "29": 74821,
        "30": 71720,
        "31": 84482,
        "32": 80581,
        "33": 87750,
        "34": 102563,
        "35": 93116,
        "36": 75937,
        "37": 70519,
        "38": 87413,
        "39": 101613,
        "40": 111777,
        "41": 106096,
        "42": 106467,
        "43": 110706,
        "44": 104071,
        "45": 113207,
        "46": 118688,
        "47": 97994,
        "48": 79642,
        "49": 102459,
        "50": 108852,
        "51": 123718,
        "52": 123821,
        "53": 106552,
        "54": 102748,
        "55": 106207,
        "56": 104827,
        "57": 120680,
        "58": 118942,
        "59": 88585
    }
]